say_hello_mauro/main.py
say_hello_mauro-0.0.1.dist-info/METADATA
say_hello_mauro-0.0.1.dist-info/WHEEL
say_hello_mauro-0.0.1.dist-info/top_level.txt
say_hello_mauro-0.0.1.dist-info/RECORD
