Metadata-Version: 2.1
Name: say-hello-mauro
Version: 0.0.1
Summary: This package says Hello to me.
Home-page: UNKNOWN
Author: Mauro M.
License: UNKNOWN
Platform: UNKNOWN
